setup.py
scopetest_1/__init__.py
scopetest_1.egg-info/PKG-INFO
scopetest_1.egg-info/SOURCES.txt
scopetest_1.egg-info/dependency_links.txt
scopetest_1.egg-info/top_level.txt
scopetest_1.egg-info/zip-safe